odoo/addons/l10n_ro_account_bank_statement_import_mt940_brd/README.rst
odoo/addons/l10n_ro_account_bank_statement_import_mt940_brd/__init__.py
odoo/addons/l10n_ro_account_bank_statement_import_mt940_brd/__manifest__.py
odoo/addons/l10n_ro_account_bank_statement_import_mt940_brd/i18n/l10n_ro_account_bank_statement_import_mt940_brd.pot
odoo/addons/l10n_ro_account_bank_statement_import_mt940_brd/i18n/ro.po
odoo/addons/l10n_ro_account_bank_statement_import_mt940_brd/models/__init__.py
odoo/addons/l10n_ro_account_bank_statement_import_mt940_brd/models/account_bank_statement_import.py
odoo/addons/l10n_ro_account_bank_statement_import_mt940_brd/models/account_journal.py
odoo/addons/l10n_ro_account_bank_statement_import_mt940_brd/models/mt940.py
odoo/addons/l10n_ro_account_bank_statement_import_mt940_brd/readme/CONTRIBUTORS.md
odoo/addons/l10n_ro_account_bank_statement_import_mt940_brd/readme/DESCRIPTION.md
odoo/addons/l10n_ro_account_bank_statement_import_mt940_brd/static/description/icon.png
odoo/addons/l10n_ro_account_bank_statement_import_mt940_brd/static/description/icon.svg
odoo/addons/l10n_ro_account_bank_statement_import_mt940_brd/static/description/index.html
odoo/addons/l10n_ro_account_bank_statement_import_mt940_brd/test_files/test_brd_940.txt
odoo/addons/l10n_ro_account_bank_statement_import_mt940_brd/tests/__init__.py
odoo/addons/l10n_ro_account_bank_statement_import_mt940_brd/tests/test_import_bank_statement.py
odoo_addon_l10n_ro_account_bank_statement_import_mt940_brd-18.0.0.2.0.dist-info/METADATA
odoo_addon_l10n_ro_account_bank_statement_import_mt940_brd-18.0.0.2.0.dist-info/WHEEL
odoo_addon_l10n_ro_account_bank_statement_import_mt940_brd-18.0.0.2.0.dist-info/top_level.txt
odoo_addon_l10n_ro_account_bank_statement_import_mt940_brd-18.0.0.2.0.dist-info/RECORD
